six_function_calculator.py
six_function_calculator-0.0.3.dist-info/LICENSE
six_function_calculator-0.0.3.dist-info/WHEEL
six_function_calculator-0.0.3.dist-info/METADATA
six_function_calculator-0.0.3.dist-info/RECORD
