Metadata-Version: 2.1
Name: six_function_calculator
Version: 0.0.3
Summary: six function calculator
Author-email: ADE T <ATdiscord@outlook.com>
Classifier: License :: OSI Approved :: MIT License
Project-URL: Home, https://github.com/Ne24
